pyflaskcreator/__init__.py
pyflaskcreator/flaskbuilder.py
pyflaskcreator/assets/__init__.py
pyflaskcreator/assets/app.py
pyflaskcreator/assets/flask_icon.png
pyflaskcreator/assets/welcome.css
pyflaskcreator/assets/welcome.html
pyflaskcreator-1.0.4.dist-info/LICENSE
pyflaskcreator-1.0.4.dist-info/METADATA
pyflaskcreator-1.0.4.dist-info/WHEEL
pyflaskcreator-1.0.4.dist-info/entry_points.txt
pyflaskcreator-1.0.4.dist-info/top_level.txt
pyflaskcreator-1.0.4.dist-info/RECORD
