Metadata-Version: 2.1
Name: pyflaskcreator
Version: 1.0.4
Summary: Package that creates a simple Flask project structure to use in new projects
Home-page: https://github.com/Jael-G/pyflaskcreator
Author: Jael Gonzalez
License: UNKNOWN
Platform: UNKNOWN
License-File: LICENSE
Requires-Dist: Flask
